fairsharing_client/__init__.py
fairsharing_client/__main__.py
fairsharing_client/api.py
fairsharing_client/cli.py
fairsharing_client/py.typed
fairsharing_client/version.py
fairsharing_client-0.3.0.dist-info/licenses/LICENSE
fairsharing_client-0.3.0.dist-info/WHEEL
fairsharing_client-0.3.0.dist-info/entry_points.txt
fairsharing_client-0.3.0.dist-info/METADATA
fairsharing_client-0.3.0.dist-info/RECORD
